colcon_poetry_ros/__init__.py
colcon_poetry_ros/config.py
colcon_poetry_ros/package.py
colcon_poetry_ros/dependencies/__init__.py
colcon_poetry_ros/dependencies/install.py
colcon_poetry_ros/package_augmentation/__init__.py
colcon_poetry_ros/package_augmentation/poetry.py
colcon_poetry_ros/package_identification/__init__.py
colcon_poetry_ros/package_identification/poetry.py
colcon_poetry_ros/task/__init__.py
colcon_poetry_ros/task/poetry/__init__.py
colcon_poetry_ros/task/poetry/build.py
colcon_poetry_ros/task/poetry/test.py
colcon_poetry_ros-0.9.0.dist-info/LICENSE
colcon_poetry_ros-0.9.0.dist-info/METADATA
colcon_poetry_ros-0.9.0.dist-info/WHEEL
colcon_poetry_ros-0.9.0.dist-info/entry_points.txt
colcon_poetry_ros-0.9.0.dist-info/top_level.txt
colcon_poetry_ros-0.9.0.dist-info/zip-safe
colcon_poetry_ros-0.9.0.dist-info/RECORD
