Metadata-Version: 2.1
Name: colcon-poetry-ros
Version: 0.9.0
Summary: A Colcon extension providing support for Python projects that use Poetry
Home-page: https://github.com/UrbanMachine/colcon-poetry-ros
Author: Urban Machine
Author-email: info@urbanmachine.build
Maintainer: Urban Machine
Maintainer-email: info@urbanmachine.build
License: BSD-3-Clause
Keywords: colcon
Classifier: Development Status :: 3 - Alpha
Classifier: Environment :: Plugins
Classifier: Intended Audience :: Developers
Classifier: Programming Language :: Python
Classifier: Topic :: Software Development :: Build Tools
Classifier: License :: OSI Approved :: BSD License
License-File: LICENSE
Requires-Dist: colcon-core ~=0.6
Requires-Dist: toml ~=0.10
Requires-Dist: packaging
Requires-Dist: setuptools
